gpt3datagen/__init__.py
gpt3datagen/prepare.py
gpt3datagen/utils.py
gpt3datagen/datasets/__init__.py
gpt3datagen/datasets/classification.py
gpt3datagen/datasets/condition_generation.py
gpt3datagen/datasets/news_articles.py
gpt3datagen-1.0.3.dist-info/LICENCE.txt
gpt3datagen-1.0.3.dist-info/METADATA
gpt3datagen-1.0.3.dist-info/WHEEL
gpt3datagen-1.0.3.dist-info/entry_points.txt
gpt3datagen-1.0.3.dist-info/top_level.txt
gpt3datagen-1.0.3.dist-info/RECORD
