Metadata-Version: 2.1
Name: gpt3datagen
Version: 1.0.3
Summary: Fine-Tune GPT-3 Data Generator is a python package that generate fake datasets.
Home-page: https://github.com/donwany/gpt3datagen
Author: Theophilus Siameh
Author-email: theodondre@gmail.com
License: MIT License
Keywords: GPT3,GPT3 DataGen,Sample Faker,DataGen,Fine-Tune
Platform: any
Classifier: Development Status :: 5 - Production/Stable
Classifier: Environment :: Console
Classifier: Intended Audience :: Developers
Classifier: Programming Language :: Python
Classifier: Programming Language :: Python :: 3
Classifier: Programming Language :: Python :: 3 :: Only
Classifier: Programming Language :: Python :: 3.7
Classifier: Programming Language :: Python :: 3.8
Classifier: Programming Language :: Python :: 3.9
Classifier: Programming Language :: Python :: 3.10
Classifier: Programming Language :: Python :: 3.11
Classifier: Programming Language :: Python :: Implementation :: CPython
Classifier: Programming Language :: Python :: Implementation :: PyPy
Classifier: Topic :: Software Development :: Libraries :: Python Modules
Classifier: Topic :: Software Development :: Testing
Classifier: Topic :: Utilities
Requires-Python: >=3.7
Requires-Dist: pandas
